geneburden/__init__.py
geneburden/features.py
geneburden/samples.py
scripts/__init__.py
scripts/main.py
geneburden-0.0.1.dist-info/LICENSE
geneburden-0.0.1.dist-info/METADATA
geneburden-0.0.1.dist-info/WHEEL
geneburden-0.0.1.dist-info/entry_points.txt
geneburden-0.0.1.dist-info/top_level.txt
geneburden-0.0.1.dist-info/RECORD
